juice_nbutils/__init__.py
juice_nbutils/epsdata/__init__.py
juice_nbutils/epsdata/abstract_reader.py
juice_nbutils/epsdata/datarate_reader.py
juice_nbutils/epsdata/dslatency_reader.py
juice_nbutils/epsdata/epsoutput.py
juice_nbutils/py.typed
juice_nbutils/restapi/__init__.py
juice_nbutils/restapi/sht.py
juice_nbutils-0.0.1.dist-info/LICENCE
juice_nbutils-0.0.1.dist-info/METADATA
juice_nbutils-0.0.1.dist-info/WHEEL
juice_nbutils-0.0.1.dist-info/RECORD
