Metadata-Version: 2.1
Name: juice-nbutils
Version: 0.0.1
Summary: This module provides helpers and utilities for JUICE jupyter notebooks
Home-page: https://.github.io/juice-nbutils
License: MIT
Author: JUICE SOC team
Author-email: juice_soc@cosmos.esa.int
Requires-Python: >=3.9,<4.0
Classifier: Development Status :: 4 - Beta
Classifier: Intended Audience :: Developers
Classifier: License :: OSI Approved :: MIT License
Classifier: Operating System :: OS Independent
Classifier: Programming Language :: Python
Classifier: Programming Language :: Python :: 3
Classifier: Programming Language :: Python :: 3.9
Classifier: Programming Language :: Python :: 3.10
Classifier: Programming Language :: Python :: 3.11
Classifier: Programming Language :: Python :: 3.12
Classifier: Programming Language :: Python :: 3.8
Classifier: Topic :: Software Development :: Libraries :: Python Modules
Classifier: Typing :: Typed
Requires-Dist: numpy (>=1.26.4,<2.0.0)
Requires-Dist: pandas (>=2.2.2,<3.0.0)
Project-URL: Documentation, https://.github.io/juice-nbutils
Project-URL: Repository, https://github.com//juice-nbutils
